CHANGELOG.md
LICENSE
README.md
weatherhat/__init__.py
weatherhat/history.py
weatherhat-1.0.0.dist-info/METADATA
weatherhat-1.0.0.dist-info/WHEEL
weatherhat-1.0.0.dist-info/licenses/LICENSE
weatherhat-1.0.0.dist-info/RECORD
