Metadata-Version: 2.3
Name: weatherhat
Version: 1.0.0
Summary: Library for the Pimoroni Weather HAT
Project-URL: GitHub, https://www.github.com/pimoroni/weatherhat-python
Project-URL: Homepage, https://www.pimoroni.com
Author-email: Philip Howard <phil@pimoroni.com>
Maintainer-email: Philip Howard <phil@pimoroni.com>
License: MIT License
License-File: LICENSE
Keywords: Pi,Raspberry
Classifier: Development Status :: 4 - Beta
Classifier: Intended Audience :: Developers
Classifier: License :: OSI Approved :: MIT License
Classifier: Operating System :: POSIX :: Linux
Classifier: Programming Language :: Python :: 3
Classifier: Programming Language :: Python :: 3 :: Only
Classifier: Programming Language :: Python :: 3.7
Classifier: Programming Language :: Python :: 3.8
Classifier: Programming Language :: Python :: 3.9
Classifier: Programming Language :: Python :: 3.10
Classifier: Programming Language :: Python :: 3.11
Classifier: Topic :: Software Development
Classifier: Topic :: Software Development :: Libraries
Classifier: Topic :: System :: Hardware
Requires-Python: >=3.7
Requires-Dist: ltr559>=1.0.0
Requires-Dist: pimoroni-bme280>=1.0.0
Requires-Dist: pimoroni-ioexpander>=1.0.1
Requires-Dist: smbus2
Requires-Dist: st7789>=1.0.1
